ipymock/__init__.py
ipymock/_nbdev.py
ipymock/agi.py
ipymock/browser.py
ipymock/llm.py
ipymock/mock.py
ipymock/reader.py
ipymock-1.1.2.dist-info/.ipynb_checkpoints/SOURCES-checkpoint.txt
ipymock-1.1.2.dist-info/.ipynb_checkpoints/top_level-checkpoint.txt
ipymock-1.1.2.dist-info/LICENSE
ipymock-1.1.2.dist-info/METADATA
ipymock-1.1.2.dist-info/WHEEL
ipymock-1.1.2.dist-info/top_level.txt
ipymock-1.1.2.dist-info/RECORD
