Metadata-Version: 2.1
Name: ipymock
Version: 1.1.2
Summary: A Tool that Allows You Run PyTest within Jupyter Notebook Cells
Home-page: https://github.com/seii-saintway/ipymock/tree/main/
Author: andrew
Author-email: andrew.saintway@gmail.com
License: Apache Software License 2.0
Keywords: pytest interactive jupyter
Classifier: Development Status :: 3 - Alpha
Classifier: Intended Audience :: Developers
Classifier: Natural Language :: English
Classifier: Programming Language :: Python :: 3.6
Classifier: Programming Language :: Python :: 3.7
Classifier: Programming Language :: Python :: 3.8
Classifier: License :: OSI Approved :: Apache Software License
Requires-Python: >=3.6
License-File: LICENSE
Requires-Dist: pytest (==6.*)
Requires-Dist: nbdev (==1.*)
Requires-Dist: openai (==0.*)
Requires-Dist: sentence-transformers (==2.*)
Requires-Dist: pydantic (==1.*)
Requires-Dist: langchain (==0.*)
Requires-Dist: faiss-cpu (==1.*)
Requires-Dist: duckduckgo-search (==2.*)
Requires-Dist: undetected-chromedriver (==3.*)
Requires-Dist: selenium-profiles (==2.*)
Requires-Dist: markdownify (==0.*)
